pixcrawler/__init__.py
pixcrawler/core.py
pixcrawler_sdk-0.2.0.dev1.dist-info/METADATA
pixcrawler_sdk-0.2.0.dev1.dist-info/WHEEL
pixcrawler_sdk-0.2.0.dev1.dist-info/RECORD
