Metadata-Version: 2.4
Name: pixcrawler-sdk
Version: 0.2.0.dev1
Summary: Python SDK for PixCrawler image dataset platform - simple, lightweight, ML-ready
Author-email: PixCrawler Team <team@pixcrawler.com>
License-Expression: MIT
Keywords: dataset,duplicates,image,machine-learning,sdk
Classifier: Development Status :: 4 - Beta
Classifier: Intended Audience :: Developers
Classifier: Intended Audience :: Science/Research
Classifier: License :: OSI Approved :: MIT License
Classifier: Operating System :: OS Independent
Classifier: Programming Language :: Python :: 3
Classifier: Programming Language :: Python :: 3.11
Classifier: Programming Language :: Python :: 3.12
Classifier: Programming Language :: Python :: 3.13
Classifier: Topic :: Multimedia :: Graphics
Classifier: Topic :: Scientific/Engineering :: Artificial Intelligence
Classifier: Topic :: Software Development :: Libraries :: Python Modules
Requires-Dist: azure-storage-blob>=12.0.0
Requires-Dist: requests>=2.25.0
